bangla_sentiment_analysis/__init__.py
bangla_sentiment_analysis/model.py
bangla_sentiment_analysis/predict.py
bangla_sentiment_analysis/text_process.py
bangla_sentiment_analysis-1.0.0.dist-info/LICENSE
bangla_sentiment_analysis-1.0.0.dist-info/METADATA
bangla_sentiment_analysis-1.0.0.dist-info/WHEEL
bangla_sentiment_analysis-1.0.0.dist-info/top_level.txt
bangla_sentiment_analysis-1.0.0.dist-info/RECORD
