Metadata-Version: 2.1
Name: bangla_sentiment_analysis
Version: 1.0.0
Summary: A package for Bangla text sentiment analysis using deep learning models.
Home-page: https://github.com/alamgirkabir9/bangla_sentiment_analysis
Author: Alamgir kabir
Author-email: alomgirkabir720@gmail.com
Classifier: Programming Language :: Python :: 3
Classifier: License :: OSI Approved :: MIT License
Classifier: Operating System :: OS Independent
Requires-Python: >=3.6
License-File: LICENSE
Requires-Dist: tensorflow>=2.0
Requires-Dist: scikit-learn
Requires-Dist: pandas
Requires-Dist: numpy
